CHANGES.txt
MANIFEST.in
README.rst
distribute_setup.py
setup.py
bin/add_tags_to_adapters.py
bin/add_tags_to_primers.py
bin/design_edit_metric_tags.py
bin/estimate_sequencing_error_effects.py
bin/get_tag_flows_for_454.py
bin/validate_edit_metric_tags.py
docs/citation.rst
docs/design.rst
docs/formatting.rst
docs/funding.rst
docs/helpers.rst
docs/index.rst
docs/installation.rst
docs/introduction.rst
docs/license.rst
docs/references.rst
docs/using_adapters.rst
docs/using_primers.rst
docs/validation.rst
edittag/__init__.py
edittag/helpers.py
edittag/levenshtein.py
edittag.egg-info/PKG-INFO
edittag.egg-info/SOURCES.txt
edittag.egg-info/dependency_links.txt
edittag.egg-info/top_level.txt
edittag/primer3/__init__.py
edittag/primer3/primer.py
edittag/tests/__init__.py
edittag/tests/test_c_levenshtein.py
edittag/tests/test_levenshtein.py
edittag/tests/test-data/edit_metric_tags.txt