Metadata-Version: 1.1
Name: edittag
Version: 1.1
Summary: Design and check sets of edit metric sequence tags.
Home-page: http://github.com/faircloth-lab/edittag/
Author: Brant Faircloth
Author-email: brant.faircloth+edittag@gmail.com
License: http://www.opensource.org/licenses/BSD-3-Clause
Platform: UNKNOWN
Classifier: Development Status :: 4 - Beta
Classifier: Environment :: Console
Classifier: Operating System :: OS Independent
Classifier: Intended Audience :: Science/Research
Classifier: License :: OSI Approved :: BSD License
Classifier: Programming Language :: Python
Classifier: Topic :: Scientific/Engineering :: Bio-Informatics
Requires: numpy(>=1.3)
